tscribe/__init__.py
tscribe-1.3.1.dist-info/LICENSE
tscribe-1.3.1.dist-info/METADATA
tscribe-1.3.1.dist-info/WHEEL
tscribe-1.3.1.dist-info/top_level.txt
tscribe-1.3.1.dist-info/RECORD
