Metadata-Version: 2.1
Name: tscribe
Version: 1.3.1
Summary: Produce Word Document, CSV or SQLite transcriptions using the automatic speech recognition from AWS Transcribe.
Home-page: https://github.com/kibaffo33/aws_transcribe_to_docx
Author: Robert Williams
Author-email: robertedwardwilliams@me.com
License: UNKNOWN
Platform: UNKNOWN
Classifier: License :: OSI Approved :: MIT License
Classifier: Programming Language :: Python :: 3
Classifier: Programming Language :: Python :: 3.6
Classifier: Programming Language :: Python :: 3.7
Classifier: Programming Language :: Python :: 3.8
Classifier: Operating System :: OS Independent
Requires-Dist: python-docx
Requires-Dist: matplotlib
Requires-Dist: pandas
Requires-Dist: webvtt-py
